setup.py
Novelty/__init__.py
Novelty/novelty.py
Novelty.egg-info/PKG-INFO
Novelty.egg-info/SOURCES.txt
Novelty.egg-info/dependency_links.txt
Novelty.egg-info/entry_points.txt
Novelty.egg-info/requires.txt
Novelty.egg-info/top_level.txt